Metadata-Version: 2.1
Name: odoo14-addon-account_statement_import_file_reconciliation_widget
Version: 14.0.1.0.1.dev16
Summary: Import Statement Files and Go Direct to Reconciliation
Home-page: https://github.com/OCA/bank-statement-import
Author: Akretion, Odoo Community Association (OCA)
Author-email: support@odoo-community.org
License: AGPL-3
Classifier: Programming Language :: Python
Classifier: Framework :: Odoo
Classifier: Framework :: Odoo :: 14.0
Classifier: License :: OSI Approved :: GNU Affero General Public License v3
Requires-Python: >=3.6
Requires-Dist: odoo14-addon-account-reconciliation-widget
Requires-Dist: odoo14-addon-account-statement-import
Requires-Dist: odoo<14.1dev,>=14.0a
